{"Usuarios":[{"tipo de usuario":"Administrador","nombre de usuario":"GustavoAdmin","apellido":"Acosta","correo":"gusadmin@SIGERECO.com","id":2,"nombre":"Gustavo","pais":"CR","contraseña":"gustavoadmin"},{"tipo de usuario":"Administrador","nombre de usuario":"DrexAdmin","apellido":"Guzman","correo":"drexadmin@SIGERECO.com","id":4,"nombre":"Drexler","pais":"CR","contraseña":"drexadmin"},{"tipo de usuario":"Administrador","nombre de usuario":"TaylorAdmin","apellido":"Duran Sibaja","correo":"taylorduransibaja@SIGERECO.com","id":6,"nombre":"Taylor","pais":"Costa Rica","contraseña":"tayloradmin"},{"tipo de usuario":"Administrador","nombre de usuario":"JeremyAdmin","apellido":"Guzman","correo":"jeradmin@SIGERECO.com","id":7,"nombre":"Jeremy","pais":"CR","contraseña":"jeremyadmin"},{"tipo de usuario":"Consultor","nombre de usuario":"Profe Monica","apellido":"Munoz","correo":"MONICA.MUNOZ@ucr.ac.c","id":16,"nombre":"Monica","pais":"CR","contraseña":"usuario1"}]}